{
  "_fv": 43,
  "_type": "item",
  "definition": {
    "renderType": 1,
    "texture": "seringa",
    "customModelName": "seringa:default",
    "name": "Syringe",
    "rarity": "COMMON",
    "creativeTab": {
      "value": "CUSTOM:ItensCreativeTab"
    },
    "stackSize": 1,
    "enchantability": 0,
    "useDuration": 0,
    "toolType": 1.0,
    "damageCount": 238,
    "recipeRemainder": {
      "value": ""
    },
    "destroyAnyBlock": false,
    "immuneToFire": false,
    "stayInGridWhenCrafting": true,
    "damageOnCrafting": true,
    "enableMeleeDamage": true,
    "damageVsEntity": 2.0,
    "hasGlow": false,
    "guiBoundTo": "<NONE>",
    "inventorySize": 9,
    "inventoryStackSize": 64,
    "onEntityHitWith": {
      "name": "SyringeLivingEntityIsHitWithItem"
    },
    "isFood": false,
    "nutritionalValue": 4,
    "saturation": 0.3,
    "eatResultItem": {
      "value": ""
    },
    "isMeat": false,
    "isAlwaysEdible": false,
    "animation": "none"
  }
}