{
  "parent": "block/cube",
  "textures": {
    "down": "aetherium_resources_reloaded:block/glitchblock04",
    "up": "aetherium_resources_reloaded:block/glitchblock04",
    "north": "aetherium_resources_reloaded:block/glitchblock04",
    "east": "aetherium_resources_reloaded:block/glitchblock04",
    "south": "aetherium_resources_reloaded:block/glitchblock04",
    "west": "aetherium_resources_reloaded:block/glitchblock04",
    "particle": "aetherium_resources_reloaded:block/glitchblock04"
  },
  "render_type": "translucent"
}